sc_backtest/__init__.py
sc_backtest/backtest.py
sc_backtest/data_set.py
sc_backtest/dataset.py
sc_backtest/df_func.py
sc_backtest/private_func.py
sc_backtest/sc_backtest.py
sc_backtest/simpletest.py
sc_backtest/ta_personal.py
sc_backtest/ta_personal3.py
sc_backtest/technical_analysis.py
sc_backtest/dataset/_adj_close.csv
sc_backtest/dataset/_adj_close_price.csv
sc_backtest/dataset/_adj_high_price.csv
sc_backtest/dataset/_adj_low_price.csv
sc_backtest/dataset/_adj_open_price.csv
sc_backtest/dataset/_close.csv
sc_backtest/dataset/_openint.csv
sc_backtest/dataset/_value.csv
sc_backtest/dataset/_volume.csv
sc_backtest-0.1.14.dist-info/LICENSE.txt
sc_backtest-0.1.14.dist-info/METADATA
sc_backtest-0.1.14.dist-info/WHEEL
sc_backtest-0.1.14.dist-info/top_level.txt
sc_backtest-0.1.14.dist-info/RECORD
