Metadata-Version: 2.1
Name: sc-backtest
Version: 0.1.14
Summary: Index future simple stat and time-series test module
Home-page: https://pypi.org/project/sc-backtest/
Author: Chang.Sun
Author-email: ynsfsc@126.com
License: UNKNOWN
Platform: UNKNOWN
Classifier: Programming Language :: Python :: 3
Classifier: License :: OSI Approved :: MIT License
Classifier: Operating System :: OS Independent
Requires-Python: >=3.7
Requires-Dist: pandas (>=1.3.1)
Requires-Dist: numpy (>=1.1)
Requires-Dist: ta (>=0.7.0)
Requires-Dist: seaborn (>=0.10.0)
Requires-Dist: chinesecalendar (>=1.8.0)
